[
    {
        "total_steps": 2048,
        "log_entries": 1,
        "mean_reward_last_n_eps": -304.79375708360675,
        "time_elapsed": 0.08628988265991211,
        "steps_per_second": 23793.778092937708,
        "mean_actor_loss": null,
        "mean_qf1_loss": null,
        "mean_qf2_loss": null,
        "mean_alpha": null,
        "mean_policy_entropy": null
    },
    {
        "total_steps": 4096,
        "log_entries": 2,
        "mean_reward_last_n_eps": -385.89831118444664,
        "time_elapsed": 0.16904282569885254,
        "steps_per_second": 24819.370790932047,
        "mean_actor_loss": null,
        "mean_qf1_loss": null,
        "mean_qf2_loss": null,
        "mean_alpha": null,
        "mean_policy_entropy": null
    },
    {
        "total_steps": 6144,
        "log_entries": 3,
        "mean_reward_last_n_eps": -233.0862410965596,
        "time_elapsed": 9.690967082977295,
        "steps_per_second": 215.09328839727388,
        "mean_actor_loss": -12.554081043528093,
        "mean_qf1_loss": 1.241553096738937,
        "mean_qf2_loss": 1.1968414668071936,
        "mean_alpha": 0.8438242118466984,
        "mean_policy_entropy": 3.9129024301427644,
        "mean_alpha_loss": 8.355084661628817
    },
    {
        "total_steps": 8192,
        "log_entries": 4,
        "mean_reward_last_n_eps": -201.99857166540184,
        "time_elapsed": 26.683650970458984,
        "steps_per_second": 120.5282211542165,
        "mean_actor_loss": -25.425937067717314,
        "mean_qf1_loss": 1.2201206391328014,
        "mean_qf2_loss": 1.18533994583413,
        "mean_alpha": 0.5262514530913904,
        "mean_policy_entropy": 3.8643800978315994,
        "mean_alpha_loss": 5.203653129516169
    },
    {
        "total_steps": 10240,
        "log_entries": 5,
        "mean_reward_last_n_eps": -231.94137867282814,
        "time_elapsed": 43.70310187339783,
        "steps_per_second": 120.33917120983186,
        "mean_actor_loss": -32.743765365332365,
        "mean_qf1_loss": 1.5291317718219943,
        "mean_qf2_loss": 1.4966691095323768,
        "mean_alpha": 0.28168586042011157,
        "mean_policy_entropy": 2.984372788982,
        "mean_alpha_loss": 2.55031419522129
    },
    {
        "total_steps": 12288,
        "log_entries": 6,
        "mean_reward_last_n_eps": -157.72985026551916,
        "time_elapsed": 60.69528079032898,
        "steps_per_second": 120.53399001611744,
        "mean_actor_loss": -34.600815333426,
        "mean_qf1_loss": 1.4135579133580904,
        "mean_qf2_loss": 1.4207767617772333,
        "mean_alpha": 0.14967142603563843,
        "mean_policy_entropy": 1.5386193897866178,
        "mean_alpha_loss": 1.141366097232094
    },
    {
        "total_steps": 14336,
        "log_entries": 7,
        "mean_reward_last_n_eps": -161.3795781833224,
        "time_elapsed": 77.67838597297668,
        "steps_per_second": 120.59663402544395,
        "mean_actor_loss": -34.03305337205529,
        "mean_qf1_loss": 1.2427155335608404,
        "mean_qf2_loss": 1.2429598952876404,
        "mean_alpha": 0.07877812506558257,
        "mean_policy_entropy": -0.026431971693455125,
        "mean_alpha_loss": 0.478361521003535
    },
    {
        "total_steps": 16384,
        "log_entries": 8,
        "mean_reward_last_n_eps": -134.4964620607872,
        "time_elapsed": 94.69381403923035,
        "steps_per_second": 120.36688149679586,
        "mean_actor_loss": -32.646171749569476,
        "mean_qf1_loss": 1.0913607507245615,
        "mean_qf2_loss": 1.1024151426390745,
        "mean_alpha": 0.040873914964322466,
        "mean_policy_entropy": -2.114557535824133,
        "mean_alpha_loss": 0.16390460150068975
    },
    {
        "total_steps": 18432,
        "log_entries": 9,
        "mean_reward_last_n_eps": 206.2199539367337,
        "time_elapsed": 111.68731379508972,
        "steps_per_second": 120.52251202985883,
        "mean_actor_loss": -31.861498093232512,
        "mean_qf1_loss": 1.1051949043176137,
        "mean_qf2_loss": 1.1298739693593234,
        "mean_alpha": 0.020783518893949804,
        "mean_policy_entropy": -3.732313098036684,
        "mean_alpha_loss": 0.049097204466534095
    },
    {
        "total_steps": 20480,
        "log_entries": 10,
        "mean_reward_last_n_eps": 878.325844322057,
        "time_elapsed": 128.72432899475098,
        "steps_per_second": 120.21481518230911,
        "mean_actor_loss": -32.69547928404063,
        "mean_qf1_loss": 1.1758721558144316,
        "mean_qf2_loss": 1.2213035972381476,
        "mean_alpha": 0.013230789918452501,
        "mean_policy_entropy": -5.878283789148554,
        "mean_alpha_loss": 0.0016542050873127323
    },
    {
        "total_steps": 22528,
        "log_entries": 11,
        "mean_reward_last_n_eps": 1590.3832202959766,
        "time_elapsed": 145.74187994003296,
        "steps_per_second": 120.3526428219505,
        "mean_actor_loss": -36.01835240609944,
        "mean_qf1_loss": 1.3972073764307424,
        "mean_qf2_loss": 1.4095402758393902,
        "mean_alpha": 0.017538722611789126,
        "mean_policy_entropy": -6.130528082372621,
        "mean_alpha_loss": -0.002282030386922429
    },
    {
        "total_steps": 24576,
        "log_entries": 12,
        "mean_reward_last_n_eps": 1896.8446505173179,
        "time_elapsed": 162.7935390472412,
        "steps_per_second": 120.11141882924565,
        "mean_actor_loss": -41.742129288613796,
        "mean_qf1_loss": 1.7954185064299963,
        "mean_qf2_loss": 1.8063007720047608,
        "mean_alpha": 0.02394323498265294,
        "mean_policy_entropy": -6.134151865495369,
        "mean_alpha_loss": -0.0033239522921348907
    },
    {
        "total_steps": 26624,
        "log_entries": 13,
        "mean_reward_last_n_eps": 2440.1396323867484,
        "time_elapsed": 179.8217749595642,
        "steps_per_second": 120.27667475168244,
        "mean_actor_loss": -49.48592588864267,
        "mean_qf1_loss": 2.290480772673618,
        "mean_qf2_loss": 2.3245237511582673,
        "mean_alpha": 0.03172566454668413,
        "mean_policy_entropy": -6.072112238500267,
        "mean_alpha_loss": -0.0022972469957096564
    },
    {
        "total_steps": 28672,
        "log_entries": 14,
        "mean_reward_last_n_eps": 1852.891780837274,
        "time_elapsed": 196.8402078151703,
        "steps_per_second": 120.34659624100219,
        "mean_actor_loss": -57.83385447226465,
        "mean_qf1_loss": 2.906016735592857,
        "mean_qf2_loss": 2.9667542473762296,
        "mean_alpha": 0.036996793238358805,
        "mean_policy_entropy": -6.005848370492458,
        "mean_alpha_loss": -0.00019702622682871151
    },
    {
        "total_steps": 30720,
        "log_entries": 15,
        "mean_reward_last_n_eps": 2911.5755844587266,
        "time_elapsed": 213.85686874389648,
        "steps_per_second": 120.3591065570403,
        "mean_actor_loss": -66.74830117821693,
        "mean_qf1_loss": 3.4594749155221507,
        "mean_qf2_loss": 3.557659666053951,
        "mean_alpha": 0.039609762745385524,
        "mean_policy_entropy": -6.044794857967645,
        "mean_alpha_loss": -0.0017548432233240874
    },
    {
        "total_steps": 32768,
        "log_entries": 16,
        "mean_reward_last_n_eps": 2384.4557219305566,
        "time_elapsed": 230.85870885849,
        "steps_per_second": 120.4638641837141,
        "mean_actor_loss": -76.42427966371179,
        "mean_qf1_loss": 4.120636879582889,
        "mean_qf2_loss": 4.255229684989899,
        "mean_alpha": 0.04533712847114657,
        "mean_policy_entropy": -6.03869331558235,
        "mean_alpha_loss": -0.001728783377416221
    },
    {
        "total_steps": 34816,
        "log_entries": 17,
        "mean_reward_last_n_eps": 3134.698570951637,
        "time_elapsed": 247.9415318965912,
        "steps_per_second": 119.8926472782822,
        "mean_actor_loss": -86.1610460691154,
        "mean_qf1_loss": 4.714128644554876,
        "mean_qf2_loss": 4.871194991166703,
        "mean_alpha": 0.04928403974918183,
        "mean_policy_entropy": -6.027558315079659,
        "mean_alpha_loss": -0.001352421003332438
    },
    {
        "total_steps": 36864,
        "log_entries": 18,
        "mean_reward_last_n_eps": 3324.1131794124385,
        "time_elapsed": 264.9489119052887,
        "steps_per_second": 120.42472753732977,
        "mean_actor_loss": -96.90425780415535,
        "mean_qf1_loss": 5.235872233868577,
        "mean_qf2_loss": 5.371321236947551,
        "mean_alpha": 0.054258761170785874,
        "mean_policy_entropy": -6.029203850310296,
        "mean_alpha_loss": -0.001573176504479079
    },
    {
        "total_steps": 38912,
        "log_entries": 19,
        "mean_reward_last_n_eps": 3713.9701146791817,
        "time_elapsed": 282.01929807662964,
        "steps_per_second": 119.97962582385706,
        "mean_actor_loss": -107.88453420624137,
        "mean_qf1_loss": 5.541987888980657,
        "mean_qf2_loss": 5.671200418029912,
        "mean_alpha": 0.05971961332761566,
        "mean_policy_entropy": -6.029729962116107,
        "mean_alpha_loss": -0.0017513633692942676
    },
    {
        "total_steps": 40960,
        "log_entries": 20,
        "mean_reward_last_n_eps": 4050.9599191207317,
        "time_elapsed": 299.0493130683899,
        "steps_per_second": 120.26444760130522,
        "mean_actor_loss": -119.56762573868036,
        "mean_qf1_loss": 5.758065482135862,
        "mean_qf2_loss": 5.967475151643157,
        "mean_alpha": 0.06732241225472535,
        "mean_policy_entropy": -6.036939663114026,
        "mean_alpha_loss": -0.0024293588524528786
    },
    {
        "total_steps": 43008,
        "log_entries": 21,
        "mean_reward_last_n_eps": 4221.518875991079,
        "time_elapsed": 316.0583407878876,
        "steps_per_second": 120.41221708012505,
        "mean_actor_loss": -131.50807194039226,
        "mean_qf1_loss": 6.35228539374657,
        "mean_qf2_loss": 6.539120385190472,
        "mean_alpha": 0.07494513375422684,
        "mean_policy_entropy": -6.033458391204476,
        "mean_alpha_loss": -0.0024951457351392037
    },
    {
        "total_steps": 45056,
        "log_entries": 22,
        "mean_reward_last_n_eps": 4125.628645690875,
        "time_elapsed": 333.0803530216217,
        "steps_per_second": 120.320993530085,
        "mean_actor_loss": -143.0823404714465,
        "mean_qf1_loss": 6.842477700207382,
        "mean_qf2_loss": 7.038779376074672,
        "mean_alpha": 0.08065136898949277,
        "mean_policy_entropy": -6.013725434662774,
        "mean_alpha_loss": -0.001094900825592049
    },
    {
        "total_steps": 47104,
        "log_entries": 23,
        "mean_reward_last_n_eps": 4668.785413912414,
        "time_elapsed": 350.0955798625946,
        "steps_per_second": 120.36881948523427,
        "mean_actor_loss": -154.82432385534048,
        "mean_qf1_loss": 7.192780724726617,
        "mean_qf2_loss": 7.390237513463944,
        "mean_alpha": 0.08607261625002138,
        "mean_policy_entropy": -6.015995575115085,
        "mean_alpha_loss": -0.001368081737268767
    },
    {
        "total_steps": 49152,
        "log_entries": 24,
        "mean_reward_last_n_eps": 4664.961415188347,
        "time_elapsed": 367.1061460971832,
        "steps_per_second": 120.40180352902756,
        "mean_actor_loss": -167.00552708655596,
        "mean_qf1_loss": 7.454786745365709,
        "mean_qf2_loss": 7.606952521484345,
        "mean_alpha": 0.09382965119584696,
        "mean_policy_entropy": -6.016739685088396,
        "mean_alpha_loss": -0.0015112425269308005
    },
    {
        "total_steps": 51200,
        "log_entries": 25,
        "mean_reward_last_n_eps": 4698.462905607757,
        "time_elapsed": 384.11840987205505,
        "steps_per_second": 120.38982764081793,
        "mean_actor_loss": -177.690839484334,
        "mean_qf1_loss": 7.604305639164522,
        "mean_qf2_loss": 7.808455152902752,
        "mean_alpha": 0.09843395405914634,
        "mean_policy_entropy": -6.02208323054947,
        "mean_alpha_loss": -0.0021644566340910387
    },
    {
        "total_steps": 53248,
        "log_entries": 26,
        "mean_reward_last_n_eps": 4805.096122218674,
        "time_elapsed": 401.15369391441345,
        "steps_per_second": 120.22696493295638,
        "mean_actor_loss": -188.44624391943216,
        "mean_qf1_loss": 7.727787638315931,
        "mean_qf2_loss": 7.8706286882516,
        "mean_alpha": 0.10507064256671583,
        "mean_policy_entropy": -6.010135094402358,
        "mean_alpha_loss": -0.0010308092933541957
    },
    {
        "total_steps": 55296,
        "log_entries": 27,
        "mean_reward_last_n_eps": 4869.250238555034,
        "time_elapsed": 418.1656229496002,
        "steps_per_second": 120.39232656915318,
        "mean_actor_loss": -199.10774595290422,
        "mean_qf1_loss": 7.803117239847779,
        "mean_qf2_loss": 8.00763079058379,
        "mean_alpha": 0.10994885637046536,
        "mean_policy_entropy": -6.011064270278439,
        "mean_alpha_loss": -0.001185933253168514
    },
    {
        "total_steps": 57344,
        "log_entries": 28,
        "mean_reward_last_n_eps": 5067.1163519104175,
        "time_elapsed": 435.21345496177673,
        "steps_per_second": 120.13858240652029,
        "mean_actor_loss": -208.5463024377823,
        "mean_qf1_loss": 7.849162691272795,
        "mean_qf2_loss": 8.023010207340121,
        "mean_alpha": 0.11520397746789968,
        "mean_policy_entropy": -6.008895056322217,
        "mean_alpha_loss": -0.0009791554497269317
    },
    {
        "total_steps": 59392,
        "log_entries": 29,
        "mean_reward_last_n_eps": 5087.408786538133,
        "time_elapsed": 452.22055077552795,
        "steps_per_second": 120.42799273691703,
        "mean_actor_loss": -217.65817246586084,
        "mean_qf1_loss": 7.766006400575861,
        "mean_qf2_loss": 8.045187624171376,
        "mean_alpha": 0.1193919475263101,
        "mean_policy_entropy": -6.011749764671549,
        "mean_alpha_loss": -0.0013699376087288329
    },
    {
        "total_steps": 61440,
        "log_entries": 30,
        "mean_reward_last_n_eps": 5139.938730661563,
        "time_elapsed": 469.2154049873352,
        "steps_per_second": 120.51316484473178,
        "mean_actor_loss": -226.6556410640478,
        "mean_qf1_loss": 7.830850658938289,
        "mean_qf2_loss": 8.070260078646243,
        "mean_alpha": 0.12467831288086018,
        "mean_policy_entropy": -6.0079926734324545,
        "mean_alpha_loss": -0.0009537181593941568
    },
    {
        "total_steps": 63488,
        "log_entries": 31,
        "mean_reward_last_n_eps": 5192.784180977436,
        "time_elapsed": 486.23405289649963,
        "steps_per_second": 120.34452408632032,
        "mean_actor_loss": -235.03802842646837,
        "mean_qf1_loss": 7.882004191633314,
        "mean_qf2_loss": 8.12827563029714,
        "mean_alpha": 0.12700036421301775,
        "mean_policy_entropy": -6.00596178160049,
        "mean_alpha_loss": -0.0007413349885041498
    },
    {
        "total_steps": 65536,
        "log_entries": 32,
        "mean_reward_last_n_eps": 5183.169262175039,
        "time_elapsed": 503.2395730018616,
        "steps_per_second": 120.43782823676709,
        "mean_actor_loss": -242.71467076987028,
        "mean_qf1_loss": 8.003920553717762,
        "mean_qf2_loss": 8.231965324142948,
        "mean_alpha": 0.1299918466102099,
        "mean_policy_entropy": -6.003923577256501,
        "mean_alpha_loss": -0.0004648420455168889
    },
    {
        "total_steps": 67584,
        "log_entries": 33,
        "mean_reward_last_n_eps": 5298.3035503929605,
        "time_elapsed": 520.289627790451,
        "steps_per_second": 120.12288247721169,
        "mean_actor_loss": -250.29146318137646,
        "mean_qf1_loss": 8.134747245814651,
        "mean_qf2_loss": 8.292611301643774,
        "mean_alpha": 0.13327403373841662,
        "mean_policy_entropy": -6.012570339953527,
        "mean_alpha_loss": -0.00163412041212041
    },
    {
        "total_steps": 69632,
        "log_entries": 34,
        "mean_reward_last_n_eps": 5325.148966491922,
        "time_elapsed": 537.3120560646057,
        "steps_per_second": 120.31767851616667,
        "mean_actor_loss": -257.0480892509222,
        "mean_qf1_loss": 8.207453181501478,
        "mean_qf2_loss": 8.464554292848334,
        "mean_alpha": 0.13886733414256014,
        "mean_policy_entropy": -5.996923659695312,
        "mean_alpha_loss": 0.0004697418347632265
    },
    {
        "total_steps": 71680,
        "log_entries": 35,
        "mean_reward_last_n_eps": 3500.0382370119974,
        "time_elapsed": 554.3242118358612,
        "steps_per_second": 120.39028152353478,
        "mean_actor_loss": -260.64237497746944,
        "mean_qf1_loss": 8.51290961750783,
        "mean_qf2_loss": 8.705604444025084,
        "mean_alpha": 0.13641293377440888,
        "mean_policy_entropy": -6.000823275651783,
        "mean_alpha_loss": -7.376830387784139e-05
    },
    {
        "total_steps": 73728,
        "log_entries": 36,
        "mean_reward_last_n_eps": 5310.786896970432,
        "time_elapsed": 571.346421957016,
        "steps_per_second": 120.31917673826851,
        "mean_actor_loss": -266.9264562726021,
        "mean_qf1_loss": 8.998366615036502,
        "mean_qf2_loss": 9.20131642348133,
        "mean_alpha": 0.14046475900977384,
        "mean_policy_entropy": -6.004058262100443,
        "mean_alpha_loss": -0.0005142986744886002
    },
    {
        "total_steps": 75776,
        "log_entries": 37,
        "mean_reward_last_n_eps": 5441.995086218338,
        "time_elapsed": 588.3781340122223,
        "steps_per_second": 120.25226670599137,
        "mean_actor_loss": -273.32631854712963,
        "mean_qf1_loss": 9.182275132276118,
        "mean_qf2_loss": 9.40103543899022,
        "mean_alpha": 0.1452402720315149,
        "mean_policy_entropy": -6.013211723417044,
        "mean_alpha_loss": -0.00187926568594321
    },
    {
        "total_steps": 77824,
        "log_entries": 38,
        "mean_reward_last_n_eps": 5526.406495914465,
        "time_elapsed": 605.3990578651428,
        "steps_per_second": 120.32849553999526,
        "mean_actor_loss": -279.27689447999,
        "mean_qf1_loss": 9.151681845542043,
        "mean_qf2_loss": 9.412166538415477,
        "mean_alpha": 0.1486620596551802,
        "mean_policy_entropy": -5.995533148990944,
        "mean_alpha_loss": 0.0007072185005654319
    },
    {
        "total_steps": 79872,
        "log_entries": 39,
        "mean_reward_last_n_eps": 5455.334022536988,
        "time_elapsed": 622.4279878139496,
        "steps_per_second": 120.27173543130655,
        "mean_actor_loss": -284.2154263406992,
        "mean_qf1_loss": 9.40223895967938,
        "mean_qf2_loss": 9.62629069457762,
        "mean_alpha": 0.15083386066544335,
        "mean_policy_entropy": -5.9923744143452495,
        "mean_alpha_loss": 0.0011993153589173744
    },
    {
        "total_steps": 81920,
        "log_entries": 40,
        "mean_reward_last_n_eps": 3620.938869794267,
        "time_elapsed": 639.441675901413,
        "steps_per_second": 120.38028845915336,
        "mean_actor_loss": -286.967301979661,
        "mean_qf1_loss": 9.724012051243335,
        "mean_qf2_loss": 9.953894402133301,
        "mean_alpha": 0.14902023639297113,
        "mean_policy_entropy": -6.010627951007336,
        "mean_alpha_loss": -0.0015451575754923397
    },
    {
        "total_steps": 83968,
        "log_entries": 41,
        "mean_reward_last_n_eps": 5598.368534904759,
        "time_elapsed": 656.4530937671661,
        "steps_per_second": 120.39566425982362,
        "mean_actor_loss": -292.3053739517927,
        "mean_qf1_loss": 9.776594465831295,
        "mean_qf2_loss": 10.022698755608872,
        "mean_alpha": 0.15084154180658516,
        "mean_policy_entropy": -6.002272893441841,
        "mean_alpha_loss": -0.0003211802014106979
    },
    {
        "total_steps": 86016,
        "log_entries": 42,
        "mean_reward_last_n_eps": 5623.2864167819025,
        "time_elapsed": 673.4761610031128,
        "steps_per_second": 120.31350930707015,
        "mean_actor_loss": -297.3610441237688,
        "mean_qf1_loss": 9.601285442709923,
        "mean_qf2_loss": 9.890955867944285,
        "mean_alpha": 0.15284837291983422,
        "mean_policy_entropy": -6.008426701184362,
        "mean_alpha_loss": -0.0012562332093466466
    },
    {
        "total_steps": 88064,
        "log_entries": 43,
        "mean_reward_last_n_eps": 5697.7103543187895,
        "time_elapsed": 690.4960718154907,
        "steps_per_second": 120.33560064235324,
        "mean_actor_loss": -301.80099450051785,
        "mean_qf1_loss": 9.582723247352988,
        "mean_qf2_loss": 9.807460239622742,
        "mean_alpha": 0.15461218181008007,
        "mean_policy_entropy": -5.997148169670254,
        "mean_alpha_loss": 0.0004816970511001273
    },
    {
        "total_steps": 90112,
        "log_entries": 44,
        "mean_reward_last_n_eps": 5625.292250385162,
        "time_elapsed": 707.4922947883606,
        "steps_per_second": 120.50312432330458,
        "mean_actor_loss": -305.84086583554745,
        "mean_qf1_loss": 9.62166611617431,
        "mean_qf2_loss": 9.833066190592945,
        "mean_alpha": 0.1547873586823698,
        "mean_policy_entropy": -6.007925657555461,
        "mean_alpha_loss": -0.0011750740727620723
    },
    {
        "total_steps": 92160,
        "log_entries": 45,
        "mean_reward_last_n_eps": 5734.492108946215,
        "time_elapsed": 724.5094940662384,
        "steps_per_second": 120.35543025418363,
        "mean_actor_loss": -310.9203557372093,
        "mean_qf1_loss": 9.559587855124846,
        "mean_qf2_loss": 9.800225132144988,
        "mean_alpha": 0.15836103187757544,
        "mean_policy_entropy": -5.995271496241912,
        "mean_alpha_loss": 0.0007792642877575418
    },
    {
        "total_steps": 94208,
        "log_entries": 46,
        "mean_reward_last_n_eps": 5796.633489952052,
        "time_elapsed": 741.5428128242493,
        "steps_per_second": 120.24123111048718,
        "mean_actor_loss": -314.8897943049669,
        "mean_qf1_loss": 9.518021401250735,
        "mean_qf2_loss": 9.739252384519204,
        "mean_alpha": 0.1577013220230583,
        "mean_policy_entropy": -6.004298117477447,
        "mean_alpha_loss": -0.0006370674327627057
    },
    {
        "total_steps": 96256,
        "log_entries": 47,
        "mean_reward_last_n_eps": 5911.59866695339,
        "time_elapsed": 758.57585978508,
        "steps_per_second": 120.24281327099379,
        "mean_actor_loss": -318.62246765196323,
        "mean_qf1_loss": 9.435030694119632,
        "mean_qf2_loss": 9.653845288790762,
        "mean_alpha": 0.15794197746436112,
        "mean_policy_entropy": -6.0040918490849435,
        "mean_alpha_loss": -0.0006007047584830616
    },
    {
        "total_steps": 98304,
        "log_entries": 48,
        "mean_reward_last_n_eps": 5908.901473569042,
        "time_elapsed": 775.5913248062134,
        "steps_per_second": 120.36717160075405,
        "mean_actor_loss": -322.92093928158283,
        "mean_qf1_loss": 9.431690438883379,
        "mean_qf2_loss": 9.679851528257132,
        "mean_alpha": 0.16304460284300148,
        "mean_policy_entropy": -6.002976075513288,
        "mean_alpha_loss": -0.0004409664635431909
    }
]